{
  "article_data_list": [
    {
      "filename": "2003-10-18-02-T4327ecc78dfc.html",
      "order": 2,
      "output_relpath": "articles/2003/10/2003-10-18-02-T4327ecc78dfc.html",
      "tag_list": [
        "tag-0",
        "tag-3"
      ],
      "title": "T4327ecc78dfc",
      "yyyymmdd": "2003-10-18"
    },
    {
      "filename": "2003-10-31-01-T87238d78dfbb.html",
      "order": 1,
      "output_relpath": "articles/2003/10/2003-10-31-01-T87238d78dfbb.html",
      "tag_list": [
        "tag-2",
        "tag-3"
      ],
      "title": "T87238d78dfbb",
      "yyyymmdd": "2003-10-31"
    },
    {
      "filename": "2003-10-31-02-T291b57a94843.html",
      "order": 2,
      "output_relpath": "articles/2003/10/2003-10-31-02-T291b57a94843.html",
      "tag_list": [
        "tag-0",
        "tag-3"
      ],
      "title": "T291b57a94843",
      "yyyymmdd": "2003-10-31"
    }
  ],
  "tag": "tag-3",
  "yyyymm": "2003-10"
}
